LICENSE.txt
MANIFEST.in
README.md
setup.py
C:/Users/user/betterpyhap/setup.py
C:/Users/user/betterpyhap/betterpyhap/__init__.py
C:/Users/user/betterpyhap/betterpyhap/accessory.py
C:/Users/user/betterpyhap/betterpyhap/accessory_driver.py
C:/Users/user/betterpyhap/betterpyhap/camera.py
C:/Users/user/betterpyhap/betterpyhap/characteristic.py
C:/Users/user/betterpyhap/betterpyhap/const.py
C:/Users/user/betterpyhap/betterpyhap/encoder.py
C:/Users/user/betterpyhap/betterpyhap/hap_crypto.py
C:/Users/user/betterpyhap/betterpyhap/hap_event.py
C:/Users/user/betterpyhap/betterpyhap/hap_handler.py
C:/Users/user/betterpyhap/betterpyhap/hap_protocol.py
C:/Users/user/betterpyhap/betterpyhap/hap_server.py
C:/Users/user/betterpyhap/betterpyhap/hsrp.py
C:/Users/user/betterpyhap/betterpyhap/iid_manager.py
C:/Users/user/betterpyhap/betterpyhap/loader.py
C:/Users/user/betterpyhap/betterpyhap/params.py
C:/Users/user/betterpyhap/betterpyhap/service.py
C:/Users/user/betterpyhap/betterpyhap/state.py
C:/Users/user/betterpyhap/betterpyhap/tlv.py
C:/Users/user/betterpyhap/betterpyhap/util.py
C:/Users/user/betterpyhap/betterpyhap/characteristics/__init__.py
C:/Users/user/betterpyhap/betterpyhap/characteristics/accessory_identifier.py
C:/Users/user/betterpyhap/betterpyhap/characteristics/administrator_only_access.py
C:/Users/user/betterpyhap/betterpyhap/characteristics/air_particulate_density.py
C:/Users/user/betterpyhap/betterpyhap/characteristics/air_particulate_size.py
C:/Users/user/betterpyhap/betterpyhap/characteristics/air_quality.py
C:/Users/user/betterpyhap/betterpyhap/characteristics/audio_feedback.py
C:/Users/user/betterpyhap/betterpyhap/characteristics/battery_level.py
C:/Users/user/betterpyhap/betterpyhap/characteristics/brightness.py
C:/Users/user/betterpyhap/betterpyhap/characteristics/carbon_dioxide_detected.py
C:/Users/user/betterpyhap/betterpyhap/characteristics/carbon_dioxide_level.py
C:/Users/user/betterpyhap/betterpyhap/characteristics/carbon_dioxide_peak_level.py
betterpyhap.egg-info/PKG-INFO
betterpyhap.egg-info/SOURCES.txt
betterpyhap.egg-info/dependency_links.txt
betterpyhap.egg-info/requires.txt
betterpyhap.egg-info/top_level.txt
