Metadata-Version: 2.1
Name: betterpyhap
Version: 0.1.0
Summary: A Python implementation of the HomeKit Accessory Protocol (HAP)
Home-page: https://github.com/jkubas/BetterPyHap
Author: jokubas noruisis
Author-email: noruisis.jokubas@example.com
Classifier: Development Status :: 5 - Production/Stable
Classifier: License :: OSI Approved :: Apache Software License
Classifier: Programming Language :: Python :: 3
Classifier: Programming Language :: Python :: 3.6
Classifier: Programming Language :: Python :: 3.7
Classifier: Programming Language :: Python :: 3.8
Classifier: Programming Language :: Python :: 3.9
License-File: LICENSE.txt
